COPYING
MANIFEST.in
NEWS
README
setup.py
examples/createsmf.py
examples/eventlist.py
examples/smfinfo.py
pysmf.egg-info/PKG-INFO
pysmf.egg-info/SOURCES.txt
pysmf.egg-info/dependency_links.txt
pysmf.egg-info/top_level.txt
src/smf.c
src/smf.pxd
src/smf.pyx
test/test.mid
test/test_smf.py