Metadata-Version: 1.0
Name: pysmf
Version: 0.1.1
Summary: a Python module for standard MIDI files, based on libsmf
Home-page: http://das.nasophon.de/pysmf/
Author: Dominic Sacré
Author-email: dominic.sacre@gmx.de
License: BSD
Platform: UNKNOWN
